{
    "patches": [
        {
            "label": "2026-05-05_17-05-02",
            "content": "@@ -41,142 +41,35 @@\n     \n-var dias int%0A    fmt.Scan(&dias)%0A    calorias := make(%5B%5Dfloat64, dias)%0A%0A    for i:=0; i%3Cdias; i++%7B%0A        fmt.Scan(&calorias%5Bi%5D)%0A    %7D\n+fmt.Println(%22Hello, World!%22)\n %0A%7D%0A\n",
            "lines": "5"
        },
        {
            "label": "2026-05-05_17-11-41",
            "content": "@@ -176,72 +176,7 @@\n    %7D\n-%0A%0A    calorias += calorias/dias%0A    fmt.Printf(%22%25.1%5Cf%22, calorias)\n %0A%7D%0A\n",
            "lines": "11"
        },
        {
            "label": "2026-05-05_17-14-02",
            "content": "@@ -223,16 +223,17 @@\n ntf(%22%25.1\n+%5C\n f%22, calo\n",
            "lines": "14"
        },
        {
            "label": "2026-05-05_17-14-16",
            "content": "@@ -46,23 +46,19 @@\n ar dias \n-float64\n+int\n %0A    fmt\n",
            "lines": "14"
        },
        {
            "label": "2026-05-05_17-14-35",
            "content": "@@ -186,87 +186,18 @@\n     \n-for i:=0; i%3C=dias; i++%7B%0A        calorias += calorias%0A    %7D%0A    media_calorias :\n+calorias +\n = ca\n@@ -235,14 +235,8 @@\n f%22, \n-media_\n calo\n",
            "lines": "14"
        },
        {
            "label": "2026-05-05_17-18-07",
            "content": "@@ -50,25 +50,8 @@\n ias \n-int%0A    var soma \n floa\n@@ -70,25 +70,24 @@\n Scan(&dias)%0A\n-%0A\n     calorias\n@@ -186,32 +186,33 @@\n     for i:=0; i%3C\n+=\n dias; i++%7B%0A     \n@@ -214,20 +214,24 @@\n         \n-soma\n+calorias\n  += calo\n@@ -234,19 +234,16 @@\n calorias\n-%5Bi%5D\n %0A    %7D%0A \n@@ -267,27 +267,21 @@\n  := \n-soma/float64(\n+calorias/\n dias\n-)%0A\n %0A   \n@@ -301,10 +301,8 @@\n %25.1f\n-%5Cn\n %22, m\n",
            "lines": "17"
        },
        {
            "label": "2026-05-05_17-29-21",
            "content": "@@ -133,46 +133,8 @@\n ias)\n- //exige que 'dias' (no caso) seja int\n %0A%0A  \n",
            "lines": "20"
        },
        {
            "label": "2026-05-18_17-04-38",
            "content": "package main\nimport \"fmt\"\nfunc main() {\n    var dias int\n    var soma float64\n    fmt.Scan(&dias)\n\n    calorias := make([]float64, dias) //exige que 'dias' (no caso) seja int\n\n    for i:=0; i<dias; i++{\n        fmt.Scan(&calorias[i])\n    }\n\n    for i:=0; i<dias; i++{\n        soma += calorias[i]\n    }\n    media_calorias := soma/float64(dias)\n\n    fmt.Printf(\"%.1f\\n\", media_calorias)\n}\n",
            "lines": "20"
        }
    ]
}